Workbook

Sheet Sheet6
A3: Row Labels
A4: Central
A5: North
A6: South
A7: West
A8: Grand Total

Sheet Sheet7
A3: Region | B3: Revenue By Region
A4: Central | B4: 4534.62
A5: North | B5: 1606.15
A6: South | B6: 2485.35
A7: West | B7: 628.08
A8: Grand Total | B8: 9254.2

Sheet data
A1: order_id | B1: order_date | C1: ship_date | D1: region | E1: country | F1: city | G1: customer_id | H1: customer_segment | I1: product_category | J1: product_name | K1: quantity | L1: unit_price | M1: discount | N1: shipping_cost | O1: payment_method | P1: order_status | Q1: Revenue | R1: is_returned | S1: Revenue By Region | T1: Customer Segment
A2: 10001 | B2: 44931 | C2: 44934 | D2: Central | E2: Kazakhstan | F2: Almaty | G2: C001 | H2: Consumer | I2: Electronics | J2: Laptop Pro 14 | K2: 1 | L2: 1200 | M2: 0.05 | N2: 25 | O2: Credit Card | P2: Completed | Q2: =K2*L2-(1-M2) -> 1199.05 | R2: =COUNTIFS(P2,"Returned") -> 0 | S2: =VLOOKUP(D2, Sheet7!A:B, 2, FALSE) -> 4534.62 | T2: =IFERROR(VLOOKUP(G2,customers!A:B,2,FALSE),"Unknown") -> Consumer
A3: 10002 | B3: 44933 | C3: 44936 | D3: South | E3: Kazakhstan | F3: Shymkent | G3: C002 | H3: Corporate | I3: Furniture | J3: Office Chair | K3: 3 | L3: 180 | M3: 0.1 | N3: 15 | O3: Cash | P3: Completed | Q3: =K3*L3-(1-M3) -> 539.1 | R3: =COUNTIFS(P3,"Returned") -> 0 | S3: =VLOOKUP(D3, Sheet7!A:B, 2, FALSE) -> 2485.35 | T3: =IFERROR(VLOOKUP(G3,customers!A:B,2,FALSE),"Unknown") -> Corporate
A4: 10003 | B4: 44938 | C4: 44942 | D4: North | E4: Kazakhstan | F4: Astana | G4: C003 | H4: Consumer | I4: Electronics | J4: Wireless Mouse | K4: 5 | L4: 25 | M4: 0 | N4: 5 | O4: Debit Card | P4: Completed | Q4: =K4*L4-(1-M4) -> 124 | R4: =COUNTIFS(P4,"Returned") -> 0 | S4: =VLOOKUP(D4, Sheet7!A:B, 2, FALSE) -> 1606.15 | T4: =IFERROR(VLOOKUP(G4,customers!A:B,2,FALSE),"Unknown") -> Consumer
A5: 10004 | B5: 44959 | C5: 44962 | D5: Central | E5: Kazakhstan | F5: Almaty | G5: C004 | H5: Home Office | I5: Technology | J5: Tablet 10" | K5: 2 | L5: 350 | M5: 0.15 | N5: 18 | O5: Credit Card | P5: Completed | Q5: =K5*L5-(1-M5) -> 699.15 | R5: =COUNTIFS(P5,"Returned") -> 0 | S5: =VLOOKUP(D5, Sheet7!A:B, 2, FALSE) -> 4534.62 | T5: =IFERROR(VLOOKUP(G5,customers!A:B,2,FALSE),"Unknown") -> Home Office
A6: 10005 | B6: 44972 | C6: 44975 | D6: West | E6: Kazakhstan | F6: Aktobe | G6: C005 | H6: Consumer | I6: Office Supplies | J6: Printer Paper | K6: 10 | L6: 6 | M6: 0 | N6: 7 | O6: Cash | P6: Completed | Q6: =K6*L6-(1-M6) -> 59 | R6: =COUNTIFS(P6,"Returned") -> 0 | S6: =VLOOKUP(D6, Sheet7!A:B, 2, FALSE) -> 628.08 | T6: =IFERROR(VLOOKUP(G6,customers!A:B,2,FALSE),"Unknown") -> Consumer
A7: 10006 | B7: 44988 | C7: 44993 | D7: North | E7: Kazakhstan | F7: Astana | G7: C006 | H7: Corporate | I7: Electronics | J7: Monitor 27" | K7: 2 | L7: 420 | M7: 0.08 | N7: 22 | O7: Bank Transfer | P7: Completed | Q7: =K7*L7-(1-M7) -> 839.08 | R7: =COUNTIFS(P7,"Returned") -> 0 | S7: =VLOOKUP(D7, Sheet7!A:B, 2, FALSE) -> 1606.15 | T7: =IFERROR(VLOOKUP(G7,customers!A:B,2,FALSE),"Unknown") -> Corporate
A8: 10007 | B8: 44995 | C8: 44999 | D8: South | E8: Kazakhstan | F8: Shymkent | G8: C007 | H8: Consumer | I8: Technology | J8: Smartphone X | K8: 1 | L8: 950 | M8: 0.05 | N8: 20 | O8: Credit Card | P8: Returned | Q8: =K8*L8-(1-M8) -> 949.05 | R8: =COUNTIFS(P8,"Returned") -> 1 | S8: =VLOOKUP(D8, Sheet7!A:B, 2, FALSE) -> 2485.35 | T8: =IFERROR(VLOOKUP(G8,customers!A:B,2,FALSE),"Unknown") -> Consumer
A9: 10008 | B9: 45007 | C9: 45011 | D9: Central | E9: Kazakhstan | F9: Almaty | G9: C008 | H9: Corporate | I9: Furniture | J9: Meeting Table | K9: 1 | L9: 780 | M9: 0.12 | N9: 40 | O9: Bank Transfer | P9: Completed | Q9: =K9*L9-(1-M9) -> 779.12 | R9: =COUNTIFS(P9,"Returned") -> 0 | S9: =VLOOKUP(D9, Sheet7!A:B, 2, FALSE) -> 4534.62 | T9: =IFERROR(VLOOKUP(G9,customers!A:B,2,FALSE),"Unknown") -> Corporate
A10: 10009 | B10: 45021 | C10: 45025 | D10: West | E10: Kazakhstan | F10: Atyrau | G10: C009 | H10: Home Office | I10: Office Supplies | J10: Ink Cartridge | K10: 4 | L10: 45 | M10: 0 | N10: 8 | O10: Debit Card | P10: Completed | Q10: =K10*L10-(1-M10) -> 179 | R10: =COUNTIFS(P10,"Returned") -> 0 | S10: =VLOOKUP(D10, Sheet7!A:B, 2, FALSE) -> 628.08 | T10: =IFERROR(VLOOKUP(G10,customers!A:B,2,FALSE),"Unknown") -> Home Office
A11: 10010 | B11: 45034 | C11: 45038 | D11: North | E11: Kazakhstan | F11: Astana | G11: C010 | H11: Consumer | I11: Electronics | J11: Headphones | K11: 2 | L11: 85 | M11: 0.07 | N11: 10 | O11: Credit Card | P11: Completed | Q11: =K11*L11-(1-M11) -> 169.07 | R11: =COUNTIFS(P11,"Returned") -> 0 | S11: =VLOOKUP(D11, Sheet7!A:B, 2, FALSE) -> 1606.15 | T11: =IFERROR(VLOOKUP(G11,customers!A:B,2,FALSE),"Unknown") -> Consumer
A12: 10011 | B12: 45050 | C12: 45054 | D12: Central | E12: Kazakhstan | F12: Almaty | G12: C011 | H12: Corporate | I12: Technology | J12: Laptop Air 13 | K12: 1 | L12: 980 | M12: 0.1 | N12: 25 | O12: Bank Transfer | P12: Completed | Q12: =K12*L12-(1-M12) -> 979.1 | R12: =COUNTIFS(P12,"Returned") -> 0 | S12: =VLOOKUP(D12, Sheet7!A:B, 2, FALSE) -> 4534.62 | T12: =IFERROR(VLOOKUP(G12,customers!A:B,2,FALSE),"Unknown") -> Corporate
A13: 10012 | B13: 45065 | C13: 45071 | D13: South | E13: Kazakhstan | F13: Shymkent | G13: C012 | H13: Consumer | I13: Furniture | J13: Bookshelf | K13: 2 | L13: 210 | M13: 0.05 | N13: 18 | O13: Cash | P13: Completed | Q13: =K13*L13-(1-M13) -> 419.05 | R13: =COUNTIFS(P13,"Returned") -> 0 | S13: =VLOOKUP(D13, Sheet7!A:B, 2, FALSE) -> 2485.35 | T13: =IFERROR(VLOOKUP(G13,customers!A:B,2,FALSE),"Unknown") -> Consumer
... A21: 10020 | B21: 45186 | C21: 45191 | D21: South | E21: Kazakhstan | F21: Shymkent | G21: C020 | H21: Consumer | I21: Electronics | J21: Bluetooth Speaker | K21: 2 | L21: 120 | M21: 0.05 | N21: 12 | O21: Credit Card | P21: Completed | Q21: =K21*L21-(1-M21) -> 239.05 | R21: =COUNTIFS(P21,"Returned") -> 0 | S21: =VLOOKUP(D21, Sheet7!A:B, 2, FALSE) -> 2485.35 | T21: =IFERROR(VLOOKUP(G21,customers!A:B,2,FALSE),"Unknown") -> Consumer

Sheet customers
A1: customer_id | B1: customer_segment
A2: C001 | B2: Consumer
A3: C002 | B3: Corporate
A4: C003 | B4: Consumer
A5: C004 | B5: Home Office
A6: C005 | B6: Consumer
A7: C006 | B7: Corporate
A8: C007 | B8: Consumer
A9: C008 | B9: Corporate
A10: C009 | B10: Home Office
A11: C010 | B11: Consumer
A12: C011 | B12: Corporate
... A21: C020 | B21: Consumer
